dropy/__init__.py
dropy/flight.py
dropy-0.1.0.dist-info/LICENSE
dropy-0.1.0.dist-info/METADATA
dropy-0.1.0.dist-info/WHEEL
dropy-0.1.0.dist-info/top_level.txt
dropy-0.1.0.dist-info/RECORD
