Metadata-Version: 2.1
Name: dropy
Version: 0.1.0
Summary: A simple package for a simple drone simulator created in unity
Home-page: https://github.com/gittygupta/dropy
Author: Aousnik Gupta
Author-email: guptaaousnik@gmail.com
License: MIT
Download-URL: https://github.com/gittygupta/dropy/archive/v0.1.0.tar.gz
Keywords: simulator,python,unity,flight,control,NN,training,utility
Platform: UNKNOWN
Classifier: Development Status :: 3 - Alpha
Classifier: Intended Audience :: Developers
Classifier: Topic :: Software Development :: Build Tools
Classifier: License :: OSI Approved :: MIT License
Classifier: Programming Language :: Python :: 3
Classifier: Programming Language :: Python :: 3.6
Classifier: Programming Language :: Python :: 3.7
Classifier: Programming Language :: Python :: 3.8
Requires-Dist: validators
Requires-Dist: pillow
Requires-Dist: pywinauto
Requires-Dist: pyautogui
